<vmap:VMAP version="1.0" xmlns:vmap="http://www.iab.net/vmap-1.0">
  <vmap:AdBreak breakId="midroll.ad-1" breakType="linear" timeOffset="00:00:00">
    <vmap:AdSource id="1" allowMultipleAds="true" followRedirects="true">
      <vmap:VASTAdData>
        <VAST version="4.1">
          <Ad id="POD_AD-ID_001" sequence="1">
            <InLine>
              <AdSystem>&#xA;Test Adserver&#xA; </AdSystem>
              <AdTitle>&#xA;Ad That Test-Adserver Wants Player To See #1&#xA; </AdTitle>
              <Impression id="IMPRESSION-ID_001"><![CDATA[
http://tv4-prism.eyevinn-test-adserver.auto.prod.osaas.io/api/v1/sessions/331cea0b-f9a0-4ad3-b07c-e552f003316d/tracking?adId=PLAY_MINITRAILER_BACHELORETTE_5_SEK_annandag_1&progress=vast
              ]]></Impression>
              <Creatives>
                <Creative id="CRETIVE-ID_001" adId="">
                  <UniversalAdId idRegistry="test-ad-id.eyevinn">&#xA;65ddb610cf302b002a96d95c1&#xA; </UniversalAdId>
                  <Linear>
                    <Duration>&#xA;00:00:05&#xA; </Duration>
                    <TrackingEvents>
                      <Tracking event="start"><![CDATA[
http://tv4-prism.eyevinn-test-adserver.auto.prod.osaas.io/api/v1/sessions/331cea0b-f9a0-4ad3-b07c-e552f003316d/tracking?adId=PLAY_MINITRAILER_BACHELORETTE_5_SEK_annandag_1&progress=0
                      ]]></Tracking>
                      <Tracking event="firstQuartile"><![CDATA[
http://tv4-prism.eyevinn-test-adserver.auto.prod.osaas.io/api/v1/sessions/331cea0b-f9a0-4ad3-b07c-e552f003316d/tracking?adId=PLAY_MINITRAILER_BACHELORETTE_5_SEK_annandag_1&progress=25
                      ]]></Tracking>
                      <Tracking event="midpoint"><![CDATA[
http://tv4-prism.eyevinn-test-adserver.auto.prod.osaas.io/api/v1/sessions/331cea0b-f9a0-4ad3-b07c-e552f003316d/tracking?adId=PLAY_MINITRAILER_BACHELORETTE_5_SEK_annandag_1&progress=50
                      ]]></Tracking>
                      <Tracking event="thirdQuartile"><![CDATA[
http://tv4-prism.eyevinn-test-adserver.auto.prod.osaas.io/api/v1/sessions/331cea0b-f9a0-4ad3-b07c-e552f003316d/tracking?adId=PLAY_MINITRAILER_BACHELORETTE_5_SEK_annandag_1&progress=75
                      ]]></Tracking>
                      <Tracking event="complete"><![CDATA[
http://tv4-prism.eyevinn-test-adserver.auto.prod.osaas.io/api/v1/sessions/331cea0b-f9a0-4ad3-b07c-e552f003316d/tracking?adId=PLAY_MINITRAILER_BACHELORETTE_5_SEK_annandag_1&progress=100
                      ]]></Tracking>
                    </TrackingEvents>
                    <VideoClicks>
                      <ClickThrough id="Eyevinn Test AdServer"><![CDATA[
https://github.com/Eyevinn/test-adserver
                      ]]></ClickThrough>
                    </VideoClicks>
                    <MediaFiles>
                      <MediaFile bitrate="10041" delivery="progressive" height="1080"
                        type="video/mp4" width="1920"><![CDATA[
https://vod.streaming.a2d.tv/promotions/trailers/65ddb610cf302b002a96d95c_PLAY_MINITRAILER_BACHELORETTE_5_SEK_annandag.mp4
                      ]]></MediaFile>
                      <MediaFile bitrate="10041" delivery="progressive" height="1080"
                        type="video/mp4" width="1920"><![CDATA[
https://vod.streaming.a2d.tv/promotions/trailers/65ddb610cf302b002a96d95c_PLAY_MINITRAILER_BACHELORETTE_5_SEK_annandag.mp4
                      ]]></MediaFile>
                    </MediaFiles>
                  </Linear>
                </Creative>
              </Creatives>
              <Extensions></Extensions>
            </InLine>
          </Ad>
          <Ad id="POD_AD-ID_002" sequence="2">
            <InLine>
              <AdSystem>&#xA;Test Adserver&#xA; </AdSystem>
              <AdTitle>&#xA;Ad That Test-Adserver Wants Player To See #2&#xA; </AdTitle>
              <Impression id="IMPRESSION-ID_002"><![CDATA[
http://tv4-prism.eyevinn-test-adserver.auto.prod.osaas.io/api/v1/sessions/331cea0b-f9a0-4ad3-b07c-e552f003316d/tracking?adId=PLAY_MINITRAILER_F_NGARNA_P__FORTET_240316_S25_ns_16_mars_2&progress=vast
              ]]></Impression>
              <Creatives>
                <Creative id="CRETIVE-ID_002" adId="">
                  <UniversalAdId idRegistry="test-ad-id.eyevinn">&#xA;65c629f095a0ad04588ec2de2&#xA; </UniversalAdId>
                  <Linear>
                    <Duration>&#xA;00:00:09&#xA; </Duration>
                    <TrackingEvents>
                      <Tracking event="start"><![CDATA[
http://tv4-prism.eyevinn-test-adserver.auto.prod.osaas.io/api/v1/sessions/331cea0b-f9a0-4ad3-b07c-e552f003316d/tracking?adId=PLAY_MINITRAILER_F_NGARNA_P__FORTET_240316_S25_ns_16_mars_2&progress=0
                      ]]></Tracking>
                      <Tracking event="firstQuartile"><![CDATA[
http://tv4-prism.eyevinn-test-adserver.auto.prod.osaas.io/api/v1/sessions/331cea0b-f9a0-4ad3-b07c-e552f003316d/tracking?adId=PLAY_MINITRAILER_F_NGARNA_P__FORTET_240316_S25_ns_16_mars_2&progress=25
                      ]]></Tracking>
                      <Tracking event="midpoint"><![CDATA[
http://tv4-prism.eyevinn-test-adserver.auto.prod.osaas.io/api/v1/sessions/331cea0b-f9a0-4ad3-b07c-e552f003316d/tracking?adId=PLAY_MINITRAILER_F_NGARNA_P__FORTET_240316_S25_ns_16_mars_2&progress=50
                      ]]></Tracking>
                      <Tracking event="thirdQuartile"><![CDATA[
http://tv4-prism.eyevinn-test-adserver.auto.prod.osaas.io/api/v1/sessions/331cea0b-f9a0-4ad3-b07c-e552f003316d/tracking?adId=PLAY_MINITRAILER_F_NGARNA_P__FORTET_240316_S25_ns_16_mars_2&progress=75
                      ]]></Tracking>
                      <Tracking event="complete"><![CDATA[
http://tv4-prism.eyevinn-test-adserver.auto.prod.osaas.io/api/v1/sessions/331cea0b-f9a0-4ad3-b07c-e552f003316d/tracking?adId=PLAY_MINITRAILER_F_NGARNA_P__FORTET_240316_S25_ns_16_mars_2&progress=100
                      ]]></Tracking>
                    </TrackingEvents>
                    <VideoClicks>
                      <ClickThrough id="Eyevinn Test AdServer"><![CDATA[
https://github.com/Eyevinn/test-adserver
                      ]]></ClickThrough>
                    </VideoClicks>
                    <MediaFiles>
                      <MediaFile bitrate="10041" delivery="progressive" height="1080"
                        type="video/mp4" width="1920"><![CDATA[
https://vod.streaming.a2d.tv/promotions/trailers/65c629f095a0ad04588ec2de_PLAY_MINITRAILER_F_NGARNA_P__FORTET_240316_S25_ns_16_mars.mp4
                      ]]></MediaFile>
                    </MediaFiles>
                  </Linear>
                </Creative>
              </Creatives>
              <Extensions></Extensions>
            </InLine>
          </Ad>
          <Ad id="POD_AD-ID_003" sequence="3">
            <InLine>
              <AdSystem>&#xA;Test Adserver&#xA; </AdSystem>
              <AdTitle>&#xA;Ad That Test-Adserver Wants Player To See #3&#xA; </AdTitle>
              <Impression id="IMPRESSION-ID_003"><![CDATA[
http://tv4-prism.eyevinn-test-adserver.auto.prod.osaas.io/api/v1/sessions/331cea0b-f9a0-4ad3-b07c-e552f003316d/tracking?adId=PLAY_MINITRAILER_MASKED_SINGER_S04_240322_NY_S_SONG_3&progress=vast
              ]]></Impression>
              <Creatives>
                <Creative id="CRETIVE-ID_003" adId="">
                  <UniversalAdId idRegistry="test-ad-id.eyevinn">&#xA;65f050b9db5f31002ade6dcc3&#xA; </UniversalAdId>
                  <Linear>
                    <Duration>&#xA;00:00:09&#xA; </Duration>
                    <TrackingEvents>
                      <Tracking event="start"><![CDATA[
http://tv4-prism.eyevinn-test-adserver.auto.prod.osaas.io/api/v1/sessions/331cea0b-f9a0-4ad3-b07c-e552f003316d/tracking?adId=PLAY_MINITRAILER_MASKED_SINGER_S04_240322_NY_S_SONG_3&progress=0
                      ]]></Tracking>
                      <Tracking event="firstQuartile"><![CDATA[
http://tv4-prism.eyevinn-test-adserver.auto.prod.osaas.io/api/v1/sessions/331cea0b-f9a0-4ad3-b07c-e552f003316d/tracking?adId=PLAY_MINITRAILER_MASKED_SINGER_S04_240322_NY_S_SONG_3&progress=25
                      ]]></Tracking>
                      <Tracking event="midpoint"><![CDATA[
http://tv4-prism.eyevinn-test-adserver.auto.prod.osaas.io/api/v1/sessions/331cea0b-f9a0-4ad3-b07c-e552f003316d/tracking?adId=PLAY_MINITRAILER_MASKED_SINGER_S04_240322_NY_S_SONG_3&progress=50
                      ]]></Tracking>
                      <Tracking event="thirdQuartile"><![CDATA[
http://tv4-prism.eyevinn-test-adserver.auto.prod.osaas.io/api/v1/sessions/331cea0b-f9a0-4ad3-b07c-e552f003316d/tracking?adId=PLAY_MINITRAILER_MASKED_SINGER_S04_240322_NY_S_SONG_3&progress=75
                      ]]></Tracking>
                      <Tracking event="complete"><![CDATA[
http://tv4-prism.eyevinn-test-adserver.auto.prod.osaas.io/api/v1/sessions/331cea0b-f9a0-4ad3-b07c-e552f003316d/tracking?adId=PLAY_MINITRAILER_MASKED_SINGER_S04_240322_NY_S_SONG_3&progress=100
                      ]]></Tracking>
                    </TrackingEvents>
                    <VideoClicks>
                      <ClickThrough id="Eyevinn Test AdServer"><![CDATA[
https://github.com/Eyevinn/test-adserver
                      ]]></ClickThrough>
                    </VideoClicks>
                    <MediaFiles>
                      <MediaFile bitrate="10041" delivery="progressive" height="1080"
                        type="video/mp4" width="1920"><![CDATA[
https://vod.streaming.a2d.tv/promotions/trailers/65f050b9db5f31002ade6dcc_PLAY_MINITRAILER_MASKED_SINGER_S04_240322_NY_S_SONG.mp4
                      ]]></MediaFile>
                    </MediaFiles>
                  </Linear>
                </Creative>
              </Creatives>
              <Extensions></Extensions>
            </InLine>
          </Ad>
          <Ad id="POD_AD-ID_004" sequence="4">
            <InLine>
              <AdSystem>&#xA;Test Adserver&#xA; </AdSystem>
              <AdTitle>&#xA;Ad That Test-Adserver Wants Player To See #4&#xA; </AdTitle>
              <Impression id="IMPRESSION-ID_004"><![CDATA[
http://tv4-prism.eyevinn-test-adserver.auto.prod.osaas.io/api/v1/sessions/331cea0b-f9a0-4ad3-b07c-e552f003316d/tracking?adId=PLAY_MINITRAILER_OXEN_S01_9s_STREAMA_4&progress=vast
              ]]></Impression>
              <Creatives>
                <Creative id="CRETIVE-ID_004" adId="">
                  <UniversalAdId idRegistry="test-ad-id.eyevinn">&#xA;65c629d53326b06d0efaa4054&#xA; </UniversalAdId>
                  <Linear>
                    <Duration>&#xA;00:00:09&#xA; </Duration>
                    <TrackingEvents>
                      <Tracking event="start"><![CDATA[
http://tv4-prism.eyevinn-test-adserver.auto.prod.osaas.io/api/v1/sessions/331cea0b-f9a0-4ad3-b07c-e552f003316d/tracking?adId=PLAY_MINITRAILER_OXEN_S01_9s_STREAMA_4&progress=0
                      ]]></Tracking>
                      <Tracking event="firstQuartile"><![CDATA[
http://tv4-prism.eyevinn-test-adserver.auto.prod.osaas.io/api/v1/sessions/331cea0b-f9a0-4ad3-b07c-e552f003316d/tracking?adId=PLAY_MINITRAILER_OXEN_S01_9s_STREAMA_4&progress=25
                      ]]></Tracking>
                      <Tracking event="midpoint"><![CDATA[
http://tv4-prism.eyevinn-test-adserver.auto.prod.osaas.io/api/v1/sessions/331cea0b-f9a0-4ad3-b07c-e552f003316d/tracking?adId=PLAY_MINITRAILER_OXEN_S01_9s_STREAMA_4&progress=50
                      ]]></Tracking>
                      <Tracking event="thirdQuartile"><![CDATA[
http://tv4-prism.eyevinn-test-adserver.auto.prod.osaas.io/api/v1/sessions/331cea0b-f9a0-4ad3-b07c-e552f003316d/tracking?adId=PLAY_MINITRAILER_OXEN_S01_9s_STREAMA_4&progress=75
                      ]]></Tracking>
                      <Tracking event="complete"><![CDATA[
http://tv4-prism.eyevinn-test-adserver.auto.prod.osaas.io/api/v1/sessions/331cea0b-f9a0-4ad3-b07c-e552f003316d/tracking?adId=PLAY_MINITRAILER_OXEN_S01_9s_STREAMA_4&progress=100
                      ]]></Tracking>
                    </TrackingEvents>
                    <VideoClicks>
                      <ClickThrough id="Eyevinn Test AdServer"><![CDATA[
https://github.com/Eyevinn/test-adserver
                      ]]></ClickThrough>
                    </VideoClicks>
                    <MediaFiles>
                      <MediaFile bitrate="10041" delivery="progressive" height="1080"
                        type="video/mp4" width="1920"><![CDATA[
https://vod.streaming.a2d.tv/promotions/trailers/65c629d53326b06d0efaa405_PLAY_MINITRAILER_OXEN_S01_9s_STREAMA.mp4
                      ]]></MediaFile>
                    </MediaFiles>
                  </Linear>
                </Creative>
              </Creatives>
              <Extensions></Extensions>
            </InLine>
          </Ad>
          <Ad id="POD_AD-ID_005" sequence="5">
            <InLine>
              <AdSystem>&#xA;Test Adserver&#xA; </AdSystem>
              <AdTitle>&#xA;Ad That Test-Adserver Wants Player To See #5&#xA; </AdTitle>
              <Impression id="IMPRESSION-ID_005"><![CDATA[
http://tv4-prism.eyevinn-test-adserver.auto.prod.osaas.io/api/v1/sessions/331cea0b-f9a0-4ad3-b07c-e552f003316d/tracking?adId=PLAY_LINEUP_MARS_2024_15s_XP_TV4___TRL1020203673901_5&progress=vast
              ]]></Impression>
              <Creatives>
                <Creative id="CRETIVE-ID_005" adId="">
                  <UniversalAdId idRegistry="test-ad-id.eyevinn">&#xA;65e08abd478b85002d9d4d2b5&#xA; </UniversalAdId>
                  <Linear>
                    <Duration>&#xA;00:00:15&#xA; </Duration>
                    <TrackingEvents>
                      <Tracking event="start"><![CDATA[
http://tv4-prism.eyevinn-test-adserver.auto.prod.osaas.io/api/v1/sessions/331cea0b-f9a0-4ad3-b07c-e552f003316d/tracking?adId=PLAY_LINEUP_MARS_2024_15s_XP_TV4___TRL1020203673901_5&progress=0
                      ]]></Tracking>
                      <Tracking event="firstQuartile"><![CDATA[
http://tv4-prism.eyevinn-test-adserver.auto.prod.osaas.io/api/v1/sessions/331cea0b-f9a0-4ad3-b07c-e552f003316d/tracking?adId=PLAY_LINEUP_MARS_2024_15s_XP_TV4___TRL1020203673901_5&progress=25
                      ]]></Tracking>
                      <Tracking event="midpoint"><![CDATA[
http://tv4-prism.eyevinn-test-adserver.auto.prod.osaas.io/api/v1/sessions/331cea0b-f9a0-4ad3-b07c-e552f003316d/tracking?adId=PLAY_LINEUP_MARS_2024_15s_XP_TV4___TRL1020203673901_5&progress=50
                      ]]></Tracking>
                      <Tracking event="thirdQuartile"><![CDATA[
http://tv4-prism.eyevinn-test-adserver.auto.prod.osaas.io/api/v1/sessions/331cea0b-f9a0-4ad3-b07c-e552f003316d/tracking?adId=PLAY_LINEUP_MARS_2024_15s_XP_TV4___TRL1020203673901_5&progress=75
                      ]]></Tracking>
                      <Tracking event="complete"><![CDATA[
http://tv4-prism.eyevinn-test-adserver.auto.prod.osaas.io/api/v1/sessions/331cea0b-f9a0-4ad3-b07c-e552f003316d/tracking?adId=PLAY_LINEUP_MARS_2024_15s_XP_TV4___TRL1020203673901_5&progress=100
                      ]]></Tracking>
                    </TrackingEvents>
                    <VideoClicks>
                      <ClickThrough id="Eyevinn Test AdServer"><![CDATA[
https://github.com/Eyevinn/test-adserver
                      ]]></ClickThrough>
                    </VideoClicks>
                    <MediaFiles>
                      <MediaFile bitrate="10041" delivery="progressive" height="1080"
                        type="video/mp4" width="1920"><![CDATA[
https://vod.streaming.a2d.tv/promotions/trailers/65e08abd478b85002d9d4d2b_PLAY_LINEUP_MARS_2024_15s_XP_TV4___TRL1020203673901.mp4
                      ]]></MediaFile>
                    </MediaFiles>
                  </Linear>
                </Creative>
              </Creatives>
              <Extensions></Extensions>
            </InLine>
          </Ad>
          <Ad id="POD_AD-ID_006" sequence="6">
            <InLine>
              <AdSystem>&#xA;Test Adserver&#xA; </AdSystem>
              <AdTitle>&#xA;Ad That Test-Adserver Wants Player To See #6&#xA; </AdTitle>
              <Impression id="IMPRESSION-ID_006"><![CDATA[
http://tv4-prism.eyevinn-test-adserver.auto.prod.osaas.io/api/v1/sessions/331cea0b-f9a0-4ad3-b07c-e552f003316d/tracking?adId=PLAY_MINITRAILER_BACHELORETTE_5_SEK_annandag_6&progress=vast
              ]]></Impression>
              <Creatives>
                <Creative id="CRETIVE-ID_006" adId="">
                  <UniversalAdId idRegistry="test-ad-id.eyevinn">&#xA;65ddb610cf302b002a96d95c6&#xA; </UniversalAdId>
                  <Linear>
                    <Duration>&#xA;00:00:05&#xA; </Duration>
                    <TrackingEvents>
                      <Tracking event="start"><![CDATA[
http://tv4-prism.eyevinn-test-adserver.auto.prod.osaas.io/api/v1/sessions/331cea0b-f9a0-4ad3-b07c-e552f003316d/tracking?adId=PLAY_MINITRAILER_BACHELORETTE_5_SEK_annandag_6&progress=0
                      ]]></Tracking>
                      <Tracking event="firstQuartile"><![CDATA[
http://tv4-prism.eyevinn-test-adserver.auto.prod.osaas.io/api/v1/sessions/331cea0b-f9a0-4ad3-b07c-e552f003316d/tracking?adId=PLAY_MINITRAILER_BACHELORETTE_5_SEK_annandag_6&progress=25
                      ]]></Tracking>
                      <Tracking event="midpoint"><![CDATA[
http://tv4-prism.eyevinn-test-adserver.auto.prod.osaas.io/api/v1/sessions/331cea0b-f9a0-4ad3-b07c-e552f003316d/tracking?adId=PLAY_MINITRAILER_BACHELORETTE_5_SEK_annandag_6&progress=50
                      ]]></Tracking>
                      <Tracking event="thirdQuartile"><![CDATA[
http://tv4-prism.eyevinn-test-adserver.auto.prod.osaas.io/api/v1/sessions/331cea0b-f9a0-4ad3-b07c-e552f003316d/tracking?adId=PLAY_MINITRAILER_BACHELORETTE_5_SEK_annandag_6&progress=75
                      ]]></Tracking>
                      <Tracking event="complete"><![CDATA[
http://tv4-prism.eyevinn-test-adserver.auto.prod.osaas.io/api/v1/sessions/331cea0b-f9a0-4ad3-b07c-e552f003316d/tracking?adId=PLAY_MINITRAILER_BACHELORETTE_5_SEK_annandag_6&progress=100
                      ]]></Tracking>
                    </TrackingEvents>
                    <VideoClicks>
                      <ClickThrough id="Eyevinn Test AdServer"><![CDATA[
https://github.com/Eyevinn/test-adserver
                      ]]></ClickThrough>
                    </VideoClicks>
                    <MediaFiles>
                      <MediaFile bitrate="10041" delivery="progressive" height="1080"
                        type="video/mp4" width="1920"><![CDATA[
https://vod.streaming.a2d.tv/promotions/trailers/65ddb610cf302b002a96d95c_PLAY_MINITRAILER_BACHELORETTE_5_SEK_annandag.mp4
                      ]]></MediaFile>
                    </MediaFiles>
                  </Linear>
                </Creative>
              </Creatives>
              <Extensions></Extensions>
            </InLine>
          </Ad>
          <Ad id="POD_AD-ID_007" sequence="7">
            <InLine>
              <AdSystem>&#xA;Test Adserver&#xA; </AdSystem>
              <AdTitle>&#xA;Ad That Test-Adserver Wants Player To See #7&#xA; </AdTitle>
              <Impression id="IMPRESSION-ID_007"><![CDATA[
http://tv4-prism.eyevinn-test-adserver.auto.prod.osaas.io/api/v1/sessions/331cea0b-f9a0-4ad3-b07c-e552f003316d/tracking?adId=PLAY_MINITRAILER_BACHELORETTE_5_SEK_annandag_7&progress=vast
              ]]></Impression>
              <Creatives>
                <Creative id="CRETIVE-ID_007" adId="">
                  <UniversalAdId idRegistry="test-ad-id.eyevinn">&#xA;65ddb610cf302b002a96d95c7&#xA; </UniversalAdId>
                  <Linear>
                    <Duration>&#xA;00:00:05&#xA; </Duration>
                    <TrackingEvents>
                      <Tracking event="start"><![CDATA[
http://tv4-prism.eyevinn-test-adserver.auto.prod.osaas.io/api/v1/sessions/331cea0b-f9a0-4ad3-b07c-e552f003316d/tracking?adId=PLAY_MINITRAILER_BACHELORETTE_5_SEK_annandag_7&progress=0
                      ]]></Tracking>
                      <Tracking event="firstQuartile"><![CDATA[
http://tv4-prism.eyevinn-test-adserver.auto.prod.osaas.io/api/v1/sessions/331cea0b-f9a0-4ad3-b07c-e552f003316d/tracking?adId=PLAY_MINITRAILER_BACHELORETTE_5_SEK_annandag_7&progress=25
                      ]]></Tracking>
                      <Tracking event="midpoint"><![CDATA[
http://tv4-prism.eyevinn-test-adserver.auto.prod.osaas.io/api/v1/sessions/331cea0b-f9a0-4ad3-b07c-e552f003316d/tracking?adId=PLAY_MINITRAILER_BACHELORETTE_5_SEK_annandag_7&progress=50
                      ]]></Tracking>
                      <Tracking event="thirdQuartile"><![CDATA[
http://tv4-prism.eyevinn-test-adserver.auto.prod.osaas.io/api/v1/sessions/331cea0b-f9a0-4ad3-b07c-e552f003316d/tracking?adId=PLAY_MINITRAILER_BACHELORETTE_5_SEK_annandag_7&progress=75
                      ]]></Tracking>
                      <Tracking event="complete"><![CDATA[
http://tv4-prism.eyevinn-test-adserver.auto.prod.osaas.io/api/v1/sessions/331cea0b-f9a0-4ad3-b07c-e552f003316d/tracking?adId=PLAY_MINITRAILER_BACHELORETTE_5_SEK_annandag_7&progress=100
                      ]]></Tracking>
                    </TrackingEvents>
                    <VideoClicks>
                      <ClickThrough id="Eyevinn Test AdServer"><![CDATA[
https://github.com/Eyevinn/test-adserver
                      ]]></ClickThrough>
                    </VideoClicks>
                    <MediaFiles>
                      <MediaFile bitrate="10041" delivery="progressive" height="1080"
                        type="video/mp4" width="1920"><![CDATA[
https://vod.streaming.a2d.tv/promotions/trailers/65ddb610cf302b002a96d95c_PLAY_MINITRAILER_BACHELORETTE_5_SEK_annandag.mp4
                      ]]></MediaFile>
                    </MediaFiles>
                  </Linear>
                </Creative>
              </Creatives>
              <Extensions></Extensions>
            </InLine>
          </Ad>
        </VAST>
      </vmap:VASTAdData>
    </vmap:AdSource>
    <vmap:TrackingEvents>
      <vmap:Tracking event="breakStart"><![CDATA[
 http://tv4-prism.eyevinn-test-adserver.auto.prod.osaas.io/api/v1/sessions/331cea0b-f9a0-4ad3-b07c-e552f003316d/tracking?adId=midroll.ad-1&progress=vmap 
      ]]></vmap:Tracking>
    </vmap:TrackingEvents>
  </vmap:AdBreak>
  <vmap:AdBreak breakId="midroll.ad-2" breakType="linear" timeOffset="00:05:00">
    <vmap:AdSource id="2" allowMultipleAds="true" followRedirects="true">
      <vmap:VASTAdData>
        <VAST version="4.1">
          <Ad id="POD_AD-ID_001" sequence="1">
            <InLine>
              <AdSystem>&#xA;Test Adserver&#xA; </AdSystem>
              <AdTitle>&#xA;Ad That Test-Adserver Wants Player To See #1&#xA; </AdTitle>
              <Impression id="IMPRESSION-ID_001"><![CDATA[
http://tv4-prism.eyevinn-test-adserver.auto.prod.osaas.io/api/v1/sessions/331cea0b-f9a0-4ad3-b07c-e552f003316d/tracking?adId=PLAY_MINITRAILER_BACHELORETTE_5_SEK_annandag_1&progress=vast
              ]]></Impression>
              <Creatives>
                <Creative id="CRETIVE-ID_001" adId="">
                  <UniversalAdId idRegistry="test-ad-id.eyevinn">&#xA;65ddb610cf302b002a96d95c1&#xA; </UniversalAdId>
                  <Linear>
                    <Duration>&#xA;00:00:05&#xA; </Duration>
                    <TrackingEvents>
                      <Tracking event="start"><![CDATA[
http://tv4-prism.eyevinn-test-adserver.auto.prod.osaas.io/api/v1/sessions/331cea0b-f9a0-4ad3-b07c-e552f003316d/tracking?adId=PLAY_MINITRAILER_BACHELORETTE_5_SEK_annandag_1&progress=0
                      ]]></Tracking>
                      <Tracking event="firstQuartile"><![CDATA[
http://tv4-prism.eyevinn-test-adserver.auto.prod.osaas.io/api/v1/sessions/331cea0b-f9a0-4ad3-b07c-e552f003316d/tracking?adId=PLAY_MINITRAILER_BACHELORETTE_5_SEK_annandag_1&progress=25
                      ]]></Tracking>
                      <Tracking event="midpoint"><![CDATA[
http://tv4-prism.eyevinn-test-adserver.auto.prod.osaas.io/api/v1/sessions/331cea0b-f9a0-4ad3-b07c-e552f003316d/tracking?adId=PLAY_MINITRAILER_BACHELORETTE_5_SEK_annandag_1&progress=50
                      ]]></Tracking>
                      <Tracking event="thirdQuartile"><![CDATA[
http://tv4-prism.eyevinn-test-adserver.auto.prod.osaas.io/api/v1/sessions/331cea0b-f9a0-4ad3-b07c-e552f003316d/tracking?adId=PLAY_MINITRAILER_BACHELORETTE_5_SEK_annandag_1&progress=75
                      ]]></Tracking>
                      <Tracking event="complete"><![CDATA[
http://tv4-prism.eyevinn-test-adserver.auto.prod.osaas.io/api/v1/sessions/331cea0b-f9a0-4ad3-b07c-e552f003316d/tracking?adId=PLAY_MINITRAILER_BACHELORETTE_5_SEK_annandag_1&progress=100
                      ]]></Tracking>
                    </TrackingEvents>
                    <VideoClicks>
                      <ClickThrough id="Eyevinn Test AdServer"><![CDATA[
https://github.com/Eyevinn/test-adserver
                      ]]></ClickThrough>
                    </VideoClicks>
                    <MediaFiles>
                      <MediaFile bitrate="10041" delivery="progressive" height="1080"
                        type="video/mp4" width="1920"><![CDATA[
https://vod.streaming.a2d.tv/promotions/trailers/65ddb610cf302b002a96d95c_PLAY_MINITRAILER_BACHELORETTE_5_SEK_annandag.mp4
                      ]]></MediaFile>
                    </MediaFiles>
                  </Linear>
                </Creative>
              </Creatives>
              <Extensions></Extensions>
            </InLine>
          </Ad>
          <Ad id="POD_AD-ID_002" sequence="2">
            <InLine>
              <AdSystem>&#xA;Test Adserver&#xA; </AdSystem>
              <AdTitle>&#xA;Ad That Test-Adserver Wants Player To See #2&#xA; </AdTitle>
              <Impression id="IMPRESSION-ID_002"><![CDATA[
http://tv4-prism.eyevinn-test-adserver.auto.prod.osaas.io/api/v1/sessions/331cea0b-f9a0-4ad3-b07c-e552f003316d/tracking?adId=PLAY_MINITRAILER_F_NGARNA_P__FORTET_240316_S25_ns_16_mars_2&progress=vast
              ]]></Impression>
              <Creatives>
                <Creative id="CRETIVE-ID_002" adId="">
                  <UniversalAdId idRegistry="test-ad-id.eyevinn">&#xA;65c629f095a0ad04588ec2de2&#xA; </UniversalAdId>
                  <Linear>
                    <Duration>&#xA;00:00:09&#xA; </Duration>
                    <TrackingEvents>
                      <Tracking event="start"><![CDATA[
http://tv4-prism.eyevinn-test-adserver.auto.prod.osaas.io/api/v1/sessions/331cea0b-f9a0-4ad3-b07c-e552f003316d/tracking?adId=PLAY_MINITRAILER_F_NGARNA_P__FORTET_240316_S25_ns_16_mars_2&progress=0
                      ]]></Tracking>
                      <Tracking event="firstQuartile"><![CDATA[
http://tv4-prism.eyevinn-test-adserver.auto.prod.osaas.io/api/v1/sessions/331cea0b-f9a0-4ad3-b07c-e552f003316d/tracking?adId=PLAY_MINITRAILER_F_NGARNA_P__FORTET_240316_S25_ns_16_mars_2&progress=25
                      ]]></Tracking>
                      <Tracking event="midpoint"><![CDATA[
http://tv4-prism.eyevinn-test-adserver.auto.prod.osaas.io/api/v1/sessions/331cea0b-f9a0-4ad3-b07c-e552f003316d/tracking?adId=PLAY_MINITRAILER_F_NGARNA_P__FORTET_240316_S25_ns_16_mars_2&progress=50
                      ]]></Tracking>
                      <Tracking event="thirdQuartile"><![CDATA[
http://tv4-prism.eyevinn-test-adserver.auto.prod.osaas.io/api/v1/sessions/331cea0b-f9a0-4ad3-b07c-e552f003316d/tracking?adId=PLAY_MINITRAILER_F_NGARNA_P__FORTET_240316_S25_ns_16_mars_2&progress=75
                      ]]></Tracking>
                      <Tracking event="complete"><![CDATA[
http://tv4-prism.eyevinn-test-adserver.auto.prod.osaas.io/api/v1/sessions/331cea0b-f9a0-4ad3-b07c-e552f003316d/tracking?adId=PLAY_MINITRAILER_F_NGARNA_P__FORTET_240316_S25_ns_16_mars_2&progress=100
                      ]]></Tracking>
                    </TrackingEvents>
                    <VideoClicks>
                      <ClickThrough id="Eyevinn Test AdServer"><![CDATA[
https://github.com/Eyevinn/test-adserver
                      ]]></ClickThrough>
                    </VideoClicks>
                    <MediaFiles>
                      <MediaFile bitrate="10041" delivery="progressive" height="1080"
                        type="video/mp4" width="1920"><![CDATA[
https://vod.streaming.a2d.tv/promotions/trailers/65c629f095a0ad04588ec2de_PLAY_MINITRAILER_F_NGARNA_P__FORTET_240316_S25_ns_16_mars.mp4
                      ]]></MediaFile>
                    </MediaFiles>
                  </Linear>
                </Creative>
              </Creatives>
              <Extensions></Extensions>
            </InLine>
          </Ad>
          <Ad id="POD_AD-ID_003" sequence="3">
            <InLine>
              <AdSystem>&#xA;Test Adserver&#xA; </AdSystem>
              <AdTitle>&#xA;Ad That Test-Adserver Wants Player To See #3&#xA; </AdTitle>
              <Impression id="IMPRESSION-ID_003"><![CDATA[
http://tv4-prism.eyevinn-test-adserver.auto.prod.osaas.io/api/v1/sessions/331cea0b-f9a0-4ad3-b07c-e552f003316d/tracking?adId=PLAY_MINITRAILER_MASKED_SINGER_S04_240322_NY_S_SONG_3&progress=vast
              ]]></Impression>
              <Creatives>
                <Creative id="CRETIVE-ID_003" adId="">
                  <UniversalAdId idRegistry="test-ad-id.eyevinn">&#xA;65f050b9db5f31002ade6dcc3&#xA; </UniversalAdId>
                  <Linear>
                    <Duration>&#xA;00:00:09&#xA; </Duration>
                    <TrackingEvents>
                      <Tracking event="start"><![CDATA[
http://tv4-prism.eyevinn-test-adserver.auto.prod.osaas.io/api/v1/sessions/331cea0b-f9a0-4ad3-b07c-e552f003316d/tracking?adId=PLAY_MINITRAILER_MASKED_SINGER_S04_240322_NY_S_SONG_3&progress=0
                      ]]></Tracking>
                      <Tracking event="firstQuartile"><![CDATA[
http://tv4-prism.eyevinn-test-adserver.auto.prod.osaas.io/api/v1/sessions/331cea0b-f9a0-4ad3-b07c-e552f003316d/tracking?adId=PLAY_MINITRAILER_MASKED_SINGER_S04_240322_NY_S_SONG_3&progress=25
                      ]]></Tracking>
                      <Tracking event="midpoint"><![CDATA[
http://tv4-prism.eyevinn-test-adserver.auto.prod.osaas.io/api/v1/sessions/331cea0b-f9a0-4ad3-b07c-e552f003316d/tracking?adId=PLAY_MINITRAILER_MASKED_SINGER_S04_240322_NY_S_SONG_3&progress=50
                      ]]></Tracking>
                      <Tracking event="thirdQuartile"><![CDATA[
http://tv4-prism.eyevinn-test-adserver.auto.prod.osaas.io/api/v1/sessions/331cea0b-f9a0-4ad3-b07c-e552f003316d/tracking?adId=PLAY_MINITRAILER_MASKED_SINGER_S04_240322_NY_S_SONG_3&progress=75
                      ]]></Tracking>
                      <Tracking event="complete"><![CDATA[
http://tv4-prism.eyevinn-test-adserver.auto.prod.osaas.io/api/v1/sessions/331cea0b-f9a0-4ad3-b07c-e552f003316d/tracking?adId=PLAY_MINITRAILER_MASKED_SINGER_S04_240322_NY_S_SONG_3&progress=100
                      ]]></Tracking>
                    </TrackingEvents>
                    <VideoClicks>
                      <ClickThrough id="Eyevinn Test AdServer"><![CDATA[
https://github.com/Eyevinn/test-adserver
                      ]]></ClickThrough>
                    </VideoClicks>
                    <MediaFiles>
                      <MediaFile bitrate="10041" delivery="progressive" height="1080"
                        type="video/mp4" width="1920"><![CDATA[
https://vod.streaming.a2d.tv/promotions/trailers/65f050b9db5f31002ade6dcc_PLAY_MINITRAILER_MASKED_SINGER_S04_240322_NY_S_SONG.mp4
                      ]]></MediaFile>
                    </MediaFiles>
                  </Linear>
                </Creative>
              </Creatives>
              <Extensions></Extensions>
            </InLine>
          </Ad>
          <Ad id="POD_AD-ID_004" sequence="4">
            <InLine>
              <AdSystem>&#xA;Test Adserver&#xA; </AdSystem>
              <AdTitle>&#xA;Ad That Test-Adserver Wants Player To See #4&#xA; </AdTitle>
              <Impression id="IMPRESSION-ID_004"><![CDATA[
http://tv4-prism.eyevinn-test-adserver.auto.prod.osaas.io/api/v1/sessions/331cea0b-f9a0-4ad3-b07c-e552f003316d/tracking?adId=PLAY_MINITRAILER_OXEN_S01_9s_STREAMA_4&progress=vast
              ]]></Impression>
              <Creatives>
                <Creative id="CRETIVE-ID_004" adId="">
                  <UniversalAdId idRegistry="test-ad-id.eyevinn">&#xA;65c629d53326b06d0efaa4054&#xA; </UniversalAdId>
                  <Linear>
                    <Duration>&#xA;00:00:09&#xA; </Duration>
                    <TrackingEvents>
                      <Tracking event="start"><![CDATA[
http://tv4-prism.eyevinn-test-adserver.auto.prod.osaas.io/api/v1/sessions/331cea0b-f9a0-4ad3-b07c-e552f003316d/tracking?adId=PLAY_MINITRAILER_OXEN_S01_9s_STREAMA_4&progress=0
                      ]]></Tracking>
                      <Tracking event="firstQuartile"><![CDATA[
http://tv4-prism.eyevinn-test-adserver.auto.prod.osaas.io/api/v1/sessions/331cea0b-f9a0-4ad3-b07c-e552f003316d/tracking?adId=PLAY_MINITRAILER_OXEN_S01_9s_STREAMA_4&progress=25
                      ]]></Tracking>
                      <Tracking event="midpoint"><![CDATA[
http://tv4-prism.eyevinn-test-adserver.auto.prod.osaas.io/api/v1/sessions/331cea0b-f9a0-4ad3-b07c-e552f003316d/tracking?adId=PLAY_MINITRAILER_OXEN_S01_9s_STREAMA_4&progress=50
                      ]]></Tracking>
                      <Tracking event="thirdQuartile"><![CDATA[
http://tv4-prism.eyevinn-test-adserver.auto.prod.osaas.io/api/v1/sessions/331cea0b-f9a0-4ad3-b07c-e552f003316d/tracking?adId=PLAY_MINITRAILER_OXEN_S01_9s_STREAMA_4&progress=75
                      ]]></Tracking>
                      <Tracking event="complete"><![CDATA[
http://tv4-prism.eyevinn-test-adserver.auto.prod.osaas.io/api/v1/sessions/331cea0b-f9a0-4ad3-b07c-e552f003316d/tracking?adId=PLAY_MINITRAILER_OXEN_S01_9s_STREAMA_4&progress=100
                      ]]></Tracking>
                    </TrackingEvents>
                    <VideoClicks>
                      <ClickThrough id="Eyevinn Test AdServer"><![CDATA[
https://github.com/Eyevinn/test-adserver
                      ]]></ClickThrough>
                    </VideoClicks>
                    <MediaFiles>
                      <MediaFile bitrate="10041" delivery="progressive" height="1080"
                        type="video/mp4" width="1920"><![CDATA[
https://vod.streaming.a2d.tv/promotions/trailers/65c629d53326b06d0efaa405_PLAY_MINITRAILER_OXEN_S01_9s_STREAMA.mp4
                      ]]></MediaFile>
                    </MediaFiles>
                  </Linear>
                </Creative>
              </Creatives>
              <Extensions></Extensions>
            </InLine>
          </Ad>
          <Ad id="POD_AD-ID_005" sequence="5">
            <InLine>
              <AdSystem>&#xA;Test Adserver&#xA; </AdSystem>
              <AdTitle>&#xA;Ad That Test-Adserver Wants Player To See #5&#xA; </AdTitle>
              <Impression id="IMPRESSION-ID_005"><![CDATA[
http://tv4-prism.eyevinn-test-adserver.auto.prod.osaas.io/api/v1/sessions/331cea0b-f9a0-4ad3-b07c-e552f003316d/tracking?adId=PLAY_LINEUP_MARS_2024_15s_XP_TV4___TRL1020203673901_5&progress=vast
              ]]></Impression>
              <Creatives>
                <Creative id="CRETIVE-ID_005" adId="">
                  <UniversalAdId idRegistry="test-ad-id.eyevinn">&#xA;65e08abd478b85002d9d4d2b5&#xA; </UniversalAdId>
                  <Linear>
                    <Duration>&#xA;00:00:15&#xA; </Duration>
                    <TrackingEvents>
                      <Tracking event="start"><![CDATA[
http://tv4-prism.eyevinn-test-adserver.auto.prod.osaas.io/api/v1/sessions/331cea0b-f9a0-4ad3-b07c-e552f003316d/tracking?adId=PLAY_LINEUP_MARS_2024_15s_XP_TV4___TRL1020203673901_5&progress=0
                      ]]></Tracking>
                      <Tracking event="firstQuartile"><![CDATA[
http://tv4-prism.eyevinn-test-adserver.auto.prod.osaas.io/api/v1/sessions/331cea0b-f9a0-4ad3-b07c-e552f003316d/tracking?adId=PLAY_LINEUP_MARS_2024_15s_XP_TV4___TRL1020203673901_5&progress=25
                      ]]></Tracking>
                      <Tracking event="midpoint"><![CDATA[
http://tv4-prism.eyevinn-test-adserver.auto.prod.osaas.io/api/v1/sessions/331cea0b-f9a0-4ad3-b07c-e552f003316d/tracking?adId=PLAY_LINEUP_MARS_2024_15s_XP_TV4___TRL1020203673901_5&progress=50
                      ]]></Tracking>
                      <Tracking event="thirdQuartile"><![CDATA[
http://tv4-prism.eyevinn-test-adserver.auto.prod.osaas.io/api/v1/sessions/331cea0b-f9a0-4ad3-b07c-e552f003316d/tracking?adId=PLAY_LINEUP_MARS_2024_15s_XP_TV4___TRL1020203673901_5&progress=75
                      ]]></Tracking>
                      <Tracking event="complete"><![CDATA[
http://tv4-prism.eyevinn-test-adserver.auto.prod.osaas.io/api/v1/sessions/331cea0b-f9a0-4ad3-b07c-e552f003316d/tracking?adId=PLAY_LINEUP_MARS_2024_15s_XP_TV4___TRL1020203673901_5&progress=100
                      ]]></Tracking>
                    </TrackingEvents>
                    <VideoClicks>
                      <ClickThrough id="Eyevinn Test AdServer"><![CDATA[
https://github.com/Eyevinn/test-adserver
                      ]]></ClickThrough>
                    </VideoClicks>
                    <MediaFiles>
                      <MediaFile bitrate="10041" delivery="progressive" height="1080"
                        type="video/mp4" width="1920"><![CDATA[
https://vod.streaming.a2d.tv/promotions/trailers/65e08abd478b85002d9d4d2b_PLAY_LINEUP_MARS_2024_15s_XP_TV4___TRL1020203673901.mp4
                      ]]></MediaFile>
                    </MediaFiles>
                  </Linear>
                </Creative>
              </Creatives>
              <Extensions></Extensions>
            </InLine>
          </Ad>
          <Ad id="POD_AD-ID_006" sequence="6">
            <InLine>
              <AdSystem>&#xA;Test Adserver&#xA; </AdSystem>
              <AdTitle>&#xA;Ad That Test-Adserver Wants Player To See #6&#xA; </AdTitle>
              <Impression id="IMPRESSION-ID_006"><![CDATA[
http://tv4-prism.eyevinn-test-adserver.auto.prod.osaas.io/api/v1/sessions/331cea0b-f9a0-4ad3-b07c-e552f003316d/tracking?adId=PLAY_MINITRAILER_BACHELORETTE_5_SEK_annandag_6&progress=vast
              ]]></Impression>
              <Creatives>
                <Creative id="CRETIVE-ID_006" adId="">
                  <UniversalAdId idRegistry="test-ad-id.eyevinn">&#xA;65ddb610cf302b002a96d95c6&#xA; </UniversalAdId>
                  <Linear>
                    <Duration>&#xA;00:00:05&#xA; </Duration>
                    <TrackingEvents>
                      <Tracking event="start"><![CDATA[
http://tv4-prism.eyevinn-test-adserver.auto.prod.osaas.io/api/v1/sessions/331cea0b-f9a0-4ad3-b07c-e552f003316d/tracking?adId=PLAY_MINITRAILER_BACHELORETTE_5_SEK_annandag_6&progress=0
                      ]]></Tracking>
                      <Tracking event="firstQuartile"><![CDATA[
http://tv4-prism.eyevinn-test-adserver.auto.prod.osaas.io/api/v1/sessions/331cea0b-f9a0-4ad3-b07c-e552f003316d/tracking?adId=PLAY_MINITRAILER_BACHELORETTE_5_SEK_annandag_6&progress=25
                      ]]></Tracking>
                      <Tracking event="midpoint"><![CDATA[
http://tv4-prism.eyevinn-test-adserver.auto.prod.osaas.io/api/v1/sessions/331cea0b-f9a0-4ad3-b07c-e552f003316d/tracking?adId=PLAY_MINITRAILER_BACHELORETTE_5_SEK_annandag_6&progress=50
                      ]]></Tracking>
                      <Tracking event="thirdQuartile"><![CDATA[
http://tv4-prism.eyevinn-test-adserver.auto.prod.osaas.io/api/v1/sessions/331cea0b-f9a0-4ad3-b07c-e552f003316d/tracking?adId=PLAY_MINITRAILER_BACHELORETTE_5_SEK_annandag_6&progress=75
                      ]]></Tracking>
                      <Tracking event="complete"><![CDATA[
http://tv4-prism.eyevinn-test-adserver.auto.prod.osaas.io/api/v1/sessions/331cea0b-f9a0-4ad3-b07c-e552f003316d/tracking?adId=PLAY_MINITRAILER_BACHELORETTE_5_SEK_annandag_6&progress=100
                      ]]></Tracking>
                    </TrackingEvents>
                    <VideoClicks>
                      <ClickThrough id="Eyevinn Test AdServer"><![CDATA[
https://github.com/Eyevinn/test-adserver
                      ]]></ClickThrough>
                    </VideoClicks>
                    <MediaFiles>
                      <MediaFile bitrate="10041" delivery="progressive" height="1080"
                        type="video/mp4" width="1920"><![CDATA[
https://vod.streaming.a2d.tv/promotions/trailers/65ddb610cf302b002a96d95c_PLAY_MINITRAILER_BACHELORETTE_5_SEK_annandag.mp4
                      ]]></MediaFile>
                    </MediaFiles>
                  </Linear>
                </Creative>
              </Creatives>
              <Extensions></Extensions>
            </InLine>
          </Ad>
          <Ad id="POD_AD-ID_007" sequence="7">
            <InLine>
              <AdSystem>&#xA;Test Adserver&#xA; </AdSystem>
              <AdTitle>&#xA;Ad That Test-Adserver Wants Player To See #7&#xA; </AdTitle>
              <Impression id="IMPRESSION-ID_007"><![CDATA[
http://tv4-prism.eyevinn-test-adserver.auto.prod.osaas.io/api/v1/sessions/331cea0b-f9a0-4ad3-b07c-e552f003316d/tracking?adId=PLAY_MINITRAILER_BACHELORETTE_5_SEK_annandag_7&progress=vast
              ]]></Impression>
              <Creatives>
                <Creative id="CRETIVE-ID_007" adId="">
                  <UniversalAdId idRegistry="test-ad-id.eyevinn">&#xA;65ddb610cf302b002a96d95c7&#xA; </UniversalAdId>
                  <Linear>
                    <Duration>&#xA;00:00:05&#xA; </Duration>
                    <TrackingEvents>
                      <Tracking event="start"><![CDATA[
http://tv4-prism.eyevinn-test-adserver.auto.prod.osaas.io/api/v1/sessions/331cea0b-f9a0-4ad3-b07c-e552f003316d/tracking?adId=PLAY_MINITRAILER_BACHELORETTE_5_SEK_annandag_7&progress=0
                      ]]></Tracking>
                      <Tracking event="firstQuartile"><![CDATA[
http://tv4-prism.eyevinn-test-adserver.auto.prod.osaas.io/api/v1/sessions/331cea0b-f9a0-4ad3-b07c-e552f003316d/tracking?adId=PLAY_MINITRAILER_BACHELORETTE_5_SEK_annandag_7&progress=25
                      ]]></Tracking>
                      <Tracking event="midpoint"><![CDATA[
http://tv4-prism.eyevinn-test-adserver.auto.prod.osaas.io/api/v1/sessions/331cea0b-f9a0-4ad3-b07c-e552f003316d/tracking?adId=PLAY_MINITRAILER_BACHELORETTE_5_SEK_annandag_7&progress=50
                      ]]></Tracking>
                      <Tracking event="thirdQuartile"><![CDATA[
http://tv4-prism.eyevinn-test-adserver.auto.prod.osaas.io/api/v1/sessions/331cea0b-f9a0-4ad3-b07c-e552f003316d/tracking?adId=PLAY_MINITRAILER_BACHELORETTE_5_SEK_annandag_7&progress=75
                      ]]></Tracking>
                      <Tracking event="complete"><![CDATA[
http://tv4-prism.eyevinn-test-adserver.auto.prod.osaas.io/api/v1/sessions/331cea0b-f9a0-4ad3-b07c-e552f003316d/tracking?adId=PLAY_MINITRAILER_BACHELORETTE_5_SEK_annandag_7&progress=100
                      ]]></Tracking>
                    </TrackingEvents>
                    <VideoClicks>
                      <ClickThrough id="Eyevinn Test AdServer"><![CDATA[
https://github.com/Eyevinn/test-adserver
                      ]]></ClickThrough>
                    </VideoClicks>
                    <MediaFiles>
                      <MediaFile bitrate="10041" delivery="progressive" height="1080"
                        type="video/mp4" width="1920"><![CDATA[
https://vod.streaming.a2d.tv/promotions/trailers/65ddb610cf302b002a96d95c_PLAY_MINITRAILER_BACHELORETTE_5_SEK_annandag.mp4
                      ]]></MediaFile>
                    </MediaFiles>
                  </Linear>
                </Creative>
              </Creatives>
              <Extensions></Extensions>
            </InLine>
          </Ad>
        </VAST>
      </vmap:VASTAdData>
    </vmap:AdSource>
    <vmap:TrackingEvents>
      <vmap:Tracking event="breakStart"><![CDATA[
 http://tv4-prism.eyevinn-test-adserver.auto.prod.osaas.io/api/v1/sessions/331cea0b-f9a0-4ad3-b07c-e552f003316d/tracking?adId=midroll.ad-2&progress=vmap 
      ]]></vmap:Tracking>
    </vmap:TrackingEvents>
  </vmap:AdBreak>
  <vmap:AdBreak breakId="midroll.ad-3" breakType="linear" timeOffset="00:07:00">
    <vmap:AdSource id="3" allowMultipleAds="true" followRedirects="true">
      <vmap:VASTAdData>
        <VAST version="4.1">
          <Ad id="POD_AD-ID_001" sequence="1">
            <InLine>
              <AdSystem>&#xA;Test Adserver&#xA; </AdSystem>
              <AdTitle>&#xA;Ad That Test-Adserver Wants Player To See #1&#xA; </AdTitle>
              <Impression id="IMPRESSION-ID_001"><![CDATA[
http://tv4-prism.eyevinn-test-adserver.auto.prod.osaas.io/api/v1/sessions/331cea0b-f9a0-4ad3-b07c-e552f003316d/tracking?adId=PLAY_MINITRAILER_BACHELORETTE_5_SEK_annandag_1&progress=vast
              ]]></Impression>
              <Creatives>
                <Creative id="CRETIVE-ID_001" adId="">
                  <UniversalAdId idRegistry="test-ad-id.eyevinn">&#xA;65ddb610cf302b002a96d95c1&#xA; </UniversalAdId>
                  <Linear>
                    <Duration>&#xA;00:00:05&#xA; </Duration>
                    <TrackingEvents>
                      <Tracking event="start"><![CDATA[
http://tv4-prism.eyevinn-test-adserver.auto.prod.osaas.io/api/v1/sessions/331cea0b-f9a0-4ad3-b07c-e552f003316d/tracking?adId=PLAY_MINITRAILER_BACHELORETTE_5_SEK_annandag_1&progress=0
                      ]]></Tracking>
                      <Tracking event="firstQuartile"><![CDATA[
http://tv4-prism.eyevinn-test-adserver.auto.prod.osaas.io/api/v1/sessions/331cea0b-f9a0-4ad3-b07c-e552f003316d/tracking?adId=PLAY_MINITRAILER_BACHELORETTE_5_SEK_annandag_1&progress=25
                      ]]></Tracking>
                      <Tracking event="midpoint"><![CDATA[
http://tv4-prism.eyevinn-test-adserver.auto.prod.osaas.io/api/v1/sessions/331cea0b-f9a0-4ad3-b07c-e552f003316d/tracking?adId=PLAY_MINITRAILER_BACHELORETTE_5_SEK_annandag_1&progress=50
                      ]]></Tracking>
                      <Tracking event="thirdQuartile"><![CDATA[
http://tv4-prism.eyevinn-test-adserver.auto.prod.osaas.io/api/v1/sessions/331cea0b-f9a0-4ad3-b07c-e552f003316d/tracking?adId=PLAY_MINITRAILER_BACHELORETTE_5_SEK_annandag_1&progress=75
                      ]]></Tracking>
                      <Tracking event="complete"><![CDATA[
http://tv4-prism.eyevinn-test-adserver.auto.prod.osaas.io/api/v1/sessions/331cea0b-f9a0-4ad3-b07c-e552f003316d/tracking?adId=PLAY_MINITRAILER_BACHELORETTE_5_SEK_annandag_1&progress=100
                      ]]></Tracking>
                    </TrackingEvents>
                    <VideoClicks>
                      <ClickThrough id="Eyevinn Test AdServer"><![CDATA[
https://github.com/Eyevinn/test-adserver
                      ]]></ClickThrough>
                    </VideoClicks>
                    <MediaFiles>
                      <MediaFile bitrate="10041" delivery="progressive" height="1080"
                        type="video/mp4" width="1920"><![CDATA[
https://vod.streaming.a2d.tv/promotions/trailers/65ddb610cf302b002a96d95c_PLAY_MINITRAILER_BACHELORETTE_5_SEK_annandag.mp4
                      ]]></MediaFile>
                    </MediaFiles>
                  </Linear>
                </Creative>
              </Creatives>
              <Extensions></Extensions>
            </InLine>
          </Ad>
          <Ad id="POD_AD-ID_002" sequence="2">
            <InLine>
              <AdSystem>&#xA;Test Adserver&#xA; </AdSystem>
              <AdTitle>&#xA;Ad That Test-Adserver Wants Player To See #2&#xA; </AdTitle>
              <Impression id="IMPRESSION-ID_002"><![CDATA[
http://tv4-prism.eyevinn-test-adserver.auto.prod.osaas.io/api/v1/sessions/331cea0b-f9a0-4ad3-b07c-e552f003316d/tracking?adId=PLAY_MINITRAILER_F_NGARNA_P__FORTET_240316_S25_ns_16_mars_2&progress=vast
              ]]></Impression>
              <Creatives>
                <Creative id="CRETIVE-ID_002" adId="">
                  <UniversalAdId idRegistry="test-ad-id.eyevinn">&#xA;65c629f095a0ad04588ec2de2&#xA; </UniversalAdId>
                  <Linear>
                    <Duration>&#xA;00:00:09&#xA; </Duration>
                    <TrackingEvents>
                      <Tracking event="start"><![CDATA[
http://tv4-prism.eyevinn-test-adserver.auto.prod.osaas.io/api/v1/sessions/331cea0b-f9a0-4ad3-b07c-e552f003316d/tracking?adId=PLAY_MINITRAILER_F_NGARNA_P__FORTET_240316_S25_ns_16_mars_2&progress=0
                      ]]></Tracking>
                      <Tracking event="firstQuartile"><![CDATA[
http://tv4-prism.eyevinn-test-adserver.auto.prod.osaas.io/api/v1/sessions/331cea0b-f9a0-4ad3-b07c-e552f003316d/tracking?adId=PLAY_MINITRAILER_F_NGARNA_P__FORTET_240316_S25_ns_16_mars_2&progress=25
                      ]]></Tracking>
                      <Tracking event="midpoint"><![CDATA[
http://tv4-prism.eyevinn-test-adserver.auto.prod.osaas.io/api/v1/sessions/331cea0b-f9a0-4ad3-b07c-e552f003316d/tracking?adId=PLAY_MINITRAILER_F_NGARNA_P__FORTET_240316_S25_ns_16_mars_2&progress=50
                      ]]></Tracking>
                      <Tracking event="thirdQuartile"><![CDATA[
http://tv4-prism.eyevinn-test-adserver.auto.prod.osaas.io/api/v1/sessions/331cea0b-f9a0-4ad3-b07c-e552f003316d/tracking?adId=PLAY_MINITRAILER_F_NGARNA_P__FORTET_240316_S25_ns_16_mars_2&progress=75
                      ]]></Tracking>
                      <Tracking event="complete"><![CDATA[
http://tv4-prism.eyevinn-test-adserver.auto.prod.osaas.io/api/v1/sessions/331cea0b-f9a0-4ad3-b07c-e552f003316d/tracking?adId=PLAY_MINITRAILER_F_NGARNA_P__FORTET_240316_S25_ns_16_mars_2&progress=100
                      ]]></Tracking>
                    </TrackingEvents>
                    <VideoClicks>
                      <ClickThrough id="Eyevinn Test AdServer"><![CDATA[
https://github.com/Eyevinn/test-adserver
                      ]]></ClickThrough>
                    </VideoClicks>
                    <MediaFiles>
                      <MediaFile bitrate="10041" delivery="progressive" height="1080"
                        type="video/mp4" width="1920"><![CDATA[
https://vod.streaming.a2d.tv/promotions/trailers/65c629f095a0ad04588ec2de_PLAY_MINITRAILER_F_NGARNA_P__FORTET_240316_S25_ns_16_mars.mp4
                      ]]></MediaFile>
                    </MediaFiles>
                  </Linear>
                </Creative>
              </Creatives>
              <Extensions></Extensions>
            </InLine>
          </Ad>
          <Ad id="POD_AD-ID_003" sequence="3">
            <InLine>
              <AdSystem>&#xA;Test Adserver&#xA; </AdSystem>
              <AdTitle>&#xA;Ad That Test-Adserver Wants Player To See #3&#xA; </AdTitle>
              <Impression id="IMPRESSION-ID_003"><![CDATA[
http://tv4-prism.eyevinn-test-adserver.auto.prod.osaas.io/api/v1/sessions/331cea0b-f9a0-4ad3-b07c-e552f003316d/tracking?adId=PLAY_MINITRAILER_MASKED_SINGER_S04_240322_NY_S_SONG_3&progress=vast
              ]]></Impression>
              <Creatives>
                <Creative id="CRETIVE-ID_003" adId="">
                  <UniversalAdId idRegistry="test-ad-id.eyevinn">&#xA;65f050b9db5f31002ade6dcc3&#xA; </UniversalAdId>
                  <Linear>
                    <Duration>&#xA;00:00:09&#xA; </Duration>
                    <TrackingEvents>
                      <Tracking event="start"><![CDATA[
http://tv4-prism.eyevinn-test-adserver.auto.prod.osaas.io/api/v1/sessions/331cea0b-f9a0-4ad3-b07c-e552f003316d/tracking?adId=PLAY_MINITRAILER_MASKED_SINGER_S04_240322_NY_S_SONG_3&progress=0
                      ]]></Tracking>
                      <Tracking event="firstQuartile"><![CDATA[
http://tv4-prism.eyevinn-test-adserver.auto.prod.osaas.io/api/v1/sessions/331cea0b-f9a0-4ad3-b07c-e552f003316d/tracking?adId=PLAY_MINITRAILER_MASKED_SINGER_S04_240322_NY_S_SONG_3&progress=25
                      ]]></Tracking>
                      <Tracking event="midpoint"><![CDATA[
http://tv4-prism.eyevinn-test-adserver.auto.prod.osaas.io/api/v1/sessions/331cea0b-f9a0-4ad3-b07c-e552f003316d/tracking?adId=PLAY_MINITRAILER_MASKED_SINGER_S04_240322_NY_S_SONG_3&progress=50
                      ]]></Tracking>
                      <Tracking event="thirdQuartile"><![CDATA[
http://tv4-prism.eyevinn-test-adserver.auto.prod.osaas.io/api/v1/sessions/331cea0b-f9a0-4ad3-b07c-e552f003316d/tracking?adId=PLAY_MINITRAILER_MASKED_SINGER_S04_240322_NY_S_SONG_3&progress=75
                      ]]></Tracking>
                      <Tracking event="complete"><![CDATA[
http://tv4-prism.eyevinn-test-adserver.auto.prod.osaas.io/api/v1/sessions/331cea0b-f9a0-4ad3-b07c-e552f003316d/tracking?adId=PLAY_MINITRAILER_MASKED_SINGER_S04_240322_NY_S_SONG_3&progress=100
                      ]]></Tracking>
                    </TrackingEvents>
                    <VideoClicks>
                      <ClickThrough id="Eyevinn Test AdServer"><![CDATA[
https://github.com/Eyevinn/test-adserver
                      ]]></ClickThrough>
                    </VideoClicks>
                    <MediaFiles>
                      <MediaFile bitrate="10041" delivery="progressive" height="1080"
                        type="video/mp4" width="1920"><![CDATA[
https://vod.streaming.a2d.tv/promotions/trailers/65f050b9db5f31002ade6dcc_PLAY_MINITRAILER_MASKED_SINGER_S04_240322_NY_S_SONG.mp4
                      ]]></MediaFile>
                    </MediaFiles>
                  </Linear>
                </Creative>
              </Creatives>
              <Extensions></Extensions>
            </InLine>
          </Ad>
          <Ad id="POD_AD-ID_004" sequence="4">
            <InLine>
              <AdSystem>&#xA;Test Adserver&#xA; </AdSystem>
              <AdTitle>&#xA;Ad That Test-Adserver Wants Player To See #4&#xA; </AdTitle>
              <Impression id="IMPRESSION-ID_004"><![CDATA[
http://tv4-prism.eyevinn-test-adserver.auto.prod.osaas.io/api/v1/sessions/331cea0b-f9a0-4ad3-b07c-e552f003316d/tracking?adId=PLAY_MINITRAILER_OXEN_S01_9s_STREAMA_4&progress=vast
              ]]></Impression>
              <Creatives>
                <Creative id="CRETIVE-ID_004" adId="">
                  <UniversalAdId idRegistry="test-ad-id.eyevinn">&#xA;65c629d53326b06d0efaa4054&#xA; </UniversalAdId>
                  <Linear>
                    <Duration>&#xA;00:00:09&#xA; </Duration>
                    <TrackingEvents>
                      <Tracking event="start"><![CDATA[
http://tv4-prism.eyevinn-test-adserver.auto.prod.osaas.io/api/v1/sessions/331cea0b-f9a0-4ad3-b07c-e552f003316d/tracking?adId=PLAY_MINITRAILER_OXEN_S01_9s_STREAMA_4&progress=0
                      ]]></Tracking>
                      <Tracking event="firstQuartile"><![CDATA[
http://tv4-prism.eyevinn-test-adserver.auto.prod.osaas.io/api/v1/sessions/331cea0b-f9a0-4ad3-b07c-e552f003316d/tracking?adId=PLAY_MINITRAILER_OXEN_S01_9s_STREAMA_4&progress=25
                      ]]></Tracking>
                      <Tracking event="midpoint"><![CDATA[
http://tv4-prism.eyevinn-test-adserver.auto.prod.osaas.io/api/v1/sessions/331cea0b-f9a0-4ad3-b07c-e552f003316d/tracking?adId=PLAY_MINITRAILER_OXEN_S01_9s_STREAMA_4&progress=50
                      ]]></Tracking>
                      <Tracking event="thirdQuartile"><![CDATA[
http://tv4-prism.eyevinn-test-adserver.auto.prod.osaas.io/api/v1/sessions/331cea0b-f9a0-4ad3-b07c-e552f003316d/tracking?adId=PLAY_MINITRAILER_OXEN_S01_9s_STREAMA_4&progress=75
                      ]]></Tracking>
                      <Tracking event="complete"><![CDATA[
http://tv4-prism.eyevinn-test-adserver.auto.prod.osaas.io/api/v1/sessions/331cea0b-f9a0-4ad3-b07c-e552f003316d/tracking?adId=PLAY_MINITRAILER_OXEN_S01_9s_STREAMA_4&progress=100
                      ]]></Tracking>
                    </TrackingEvents>
                    <VideoClicks>
                      <ClickThrough id="Eyevinn Test AdServer"><![CDATA[
https://github.com/Eyevinn/test-adserver
                      ]]></ClickThrough>
                    </VideoClicks>
                    <MediaFiles>
                      <MediaFile bitrate="10041" delivery="progressive" height="1080"
                        type="video/mp4" width="1920"><![CDATA[
https://vod.streaming.a2d.tv/promotions/trailers/65c629d53326b06d0efaa405_PLAY_MINITRAILER_OXEN_S01_9s_STREAMA.mp4
                      ]]></MediaFile>
                    </MediaFiles>
                  </Linear>
                </Creative>
              </Creatives>
              <Extensions></Extensions>
            </InLine>
          </Ad>
          <Ad id="POD_AD-ID_005" sequence="5">
            <InLine>
              <AdSystem>&#xA;Test Adserver&#xA; </AdSystem>
              <AdTitle>&#xA;Ad That Test-Adserver Wants Player To See #5&#xA; </AdTitle>
              <Impression id="IMPRESSION-ID_005"><![CDATA[
http://tv4-prism.eyevinn-test-adserver.auto.prod.osaas.io/api/v1/sessions/331cea0b-f9a0-4ad3-b07c-e552f003316d/tracking?adId=PLAY_LINEUP_MARS_2024_15s_XP_TV4___TRL1020203673901_5&progress=vast
              ]]></Impression>
              <Creatives>
                <Creative id="CRETIVE-ID_005" adId="">
                  <UniversalAdId idRegistry="test-ad-id.eyevinn">&#xA;65e08abd478b85002d9d4d2b5&#xA; </UniversalAdId>
                  <Linear>
                    <Duration>&#xA;00:00:15&#xA; </Duration>
                    <TrackingEvents>
                      <Tracking event="start"><![CDATA[
http://tv4-prism.eyevinn-test-adserver.auto.prod.osaas.io/api/v1/sessions/331cea0b-f9a0-4ad3-b07c-e552f003316d/tracking?adId=PLAY_LINEUP_MARS_2024_15s_XP_TV4___TRL1020203673901_5&progress=0
                      ]]></Tracking>
                      <Tracking event="firstQuartile"><![CDATA[
http://tv4-prism.eyevinn-test-adserver.auto.prod.osaas.io/api/v1/sessions/331cea0b-f9a0-4ad3-b07c-e552f003316d/tracking?adId=PLAY_LINEUP_MARS_2024_15s_XP_TV4___TRL1020203673901_5&progress=25
                      ]]></Tracking>
                      <Tracking event="midpoint"><![CDATA[
http://tv4-prism.eyevinn-test-adserver.auto.prod.osaas.io/api/v1/sessions/331cea0b-f9a0-4ad3-b07c-e552f003316d/tracking?adId=PLAY_LINEUP_MARS_2024_15s_XP_TV4___TRL1020203673901_5&progress=50
                      ]]></Tracking>
                      <Tracking event="thirdQuartile"><![CDATA[
http://tv4-prism.eyevinn-test-adserver.auto.prod.osaas.io/api/v1/sessions/331cea0b-f9a0-4ad3-b07c-e552f003316d/tracking?adId=PLAY_LINEUP_MARS_2024_15s_XP_TV4___TRL1020203673901_5&progress=75
                      ]]></Tracking>
                      <Tracking event="complete"><![CDATA[
http://tv4-prism.eyevinn-test-adserver.auto.prod.osaas.io/api/v1/sessions/331cea0b-f9a0-4ad3-b07c-e552f003316d/tracking?adId=PLAY_LINEUP_MARS_2024_15s_XP_TV4___TRL1020203673901_5&progress=100
                      ]]></Tracking>
                    </TrackingEvents>
                    <VideoClicks>
                      <ClickThrough id="Eyevinn Test AdServer"><![CDATA[
https://github.com/Eyevinn/test-adserver
                      ]]></ClickThrough>
                    </VideoClicks>
                    <MediaFiles>
                      <MediaFile bitrate="10041" delivery="progressive" height="1080"
                        type="video/mp4" width="1920"><![CDATA[
https://vod.streaming.a2d.tv/promotions/trailers/65e08abd478b85002d9d4d2b_PLAY_LINEUP_MARS_2024_15s_XP_TV4___TRL1020203673901.mp4
                      ]]></MediaFile>
                    </MediaFiles>
                  </Linear>
                </Creative>
              </Creatives>
              <Extensions></Extensions>
            </InLine>
          </Ad>
          <Ad id="POD_AD-ID_006" sequence="6">
            <InLine>
              <AdSystem>&#xA;Test Adserver&#xA; </AdSystem>
              <AdTitle>&#xA;Ad That Test-Adserver Wants Player To See #6&#xA; </AdTitle>
              <Impression id="IMPRESSION-ID_006"><![CDATA[
http://tv4-prism.eyevinn-test-adserver.auto.prod.osaas.io/api/v1/sessions/331cea0b-f9a0-4ad3-b07c-e552f003316d/tracking?adId=PLAY_MINITRAILER_BACHELORETTE_5_SEK_annandag_6&progress=vast
              ]]></Impression>
              <Creatives>
                <Creative id="CRETIVE-ID_006" adId="">
                  <UniversalAdId idRegistry="test-ad-id.eyevinn">&#xA;65ddb610cf302b002a96d95c6&#xA; </UniversalAdId>
                  <Linear>
                    <Duration>&#xA;00:00:05&#xA; </Duration>
                    <TrackingEvents>
                      <Tracking event="start"><![CDATA[
http://tv4-prism.eyevinn-test-adserver.auto.prod.osaas.io/api/v1/sessions/331cea0b-f9a0-4ad3-b07c-e552f003316d/tracking?adId=PLAY_MINITRAILER_BACHELORETTE_5_SEK_annandag_6&progress=0
                      ]]></Tracking>
                      <Tracking event="firstQuartile"><![CDATA[
http://tv4-prism.eyevinn-test-adserver.auto.prod.osaas.io/api/v1/sessions/331cea0b-f9a0-4ad3-b07c-e552f003316d/tracking?adId=PLAY_MINITRAILER_BACHELORETTE_5_SEK_annandag_6&progress=25
                      ]]></Tracking>
                      <Tracking event="midpoint"><![CDATA[
http://tv4-prism.eyevinn-test-adserver.auto.prod.osaas.io/api/v1/sessions/331cea0b-f9a0-4ad3-b07c-e552f003316d/tracking?adId=PLAY_MINITRAILER_BACHELORETTE_5_SEK_annandag_6&progress=50
                      ]]></Tracking>
                      <Tracking event="thirdQuartile"><![CDATA[
http://tv4-prism.eyevinn-test-adserver.auto.prod.osaas.io/api/v1/sessions/331cea0b-f9a0-4ad3-b07c-e552f003316d/tracking?adId=PLAY_MINITRAILER_BACHELORETTE_5_SEK_annandag_6&progress=75
                      ]]></Tracking>
                      <Tracking event="complete"><![CDATA[
http://tv4-prism.eyevinn-test-adserver.auto.prod.osaas.io/api/v1/sessions/331cea0b-f9a0-4ad3-b07c-e552f003316d/tracking?adId=PLAY_MINITRAILER_BACHELORETTE_5_SEK_annandag_6&progress=100
                      ]]></Tracking>
                    </TrackingEvents>
                    <VideoClicks>
                      <ClickThrough id="Eyevinn Test AdServer"><![CDATA[
https://github.com/Eyevinn/test-adserver
                      ]]></ClickThrough>
                    </VideoClicks>
                    <MediaFiles>
                      <MediaFile bitrate="10041" delivery="progressive" height="1080"
                        type="video/mp4" width="1920"><![CDATA[
https://vod.streaming.a2d.tv/promotions/trailers/65ddb610cf302b002a96d95c_PLAY_MINITRAILER_BACHELORETTE_5_SEK_annandag.mp4
                      ]]></MediaFile>
                    </MediaFiles>
                  </Linear>
                </Creative>
              </Creatives>
              <Extensions></Extensions>
            </InLine>
          </Ad>
          <Ad id="POD_AD-ID_007" sequence="7">
            <InLine>
              <AdSystem>&#xA;Test Adserver&#xA; </AdSystem>
              <AdTitle>&#xA;Ad That Test-Adserver Wants Player To See #7&#xA; </AdTitle>
              <Impression id="IMPRESSION-ID_007"><![CDATA[
http://tv4-prism.eyevinn-test-adserver.auto.prod.osaas.io/api/v1/sessions/331cea0b-f9a0-4ad3-b07c-e552f003316d/tracking?adId=PLAY_MINITRAILER_BACHELORETTE_5_SEK_annandag_7&progress=vast
              ]]></Impression>
              <Creatives>
                <Creative id="CRETIVE-ID_007" adId="">
                  <UniversalAdId idRegistry="test-ad-id.eyevinn">&#xA;65ddb610cf302b002a96d95c7&#xA; </UniversalAdId>
                  <Linear>
                    <Duration>&#xA;00:00:05&#xA; </Duration>
                    <TrackingEvents>
                      <Tracking event="start"><![CDATA[
http://tv4-prism.eyevinn-test-adserver.auto.prod.osaas.io/api/v1/sessions/331cea0b-f9a0-4ad3-b07c-e552f003316d/tracking?adId=PLAY_MINITRAILER_BACHELORETTE_5_SEK_annandag_7&progress=0
                      ]]></Tracking>
                      <Tracking event="firstQuartile"><![CDATA[
http://tv4-prism.eyevinn-test-adserver.auto.prod.osaas.io/api/v1/sessions/331cea0b-f9a0-4ad3-b07c-e552f003316d/tracking?adId=PLAY_MINITRAILER_BACHELORETTE_5_SEK_annandag_7&progress=25
                      ]]></Tracking>
                      <Tracking event="midpoint"><![CDATA[
http://tv4-prism.eyevinn-test-adserver.auto.prod.osaas.io/api/v1/sessions/331cea0b-f9a0-4ad3-b07c-e552f003316d/tracking?adId=PLAY_MINITRAILER_BACHELORETTE_5_SEK_annandag_7&progress=50
                      ]]></Tracking>
                      <Tracking event="thirdQuartile"><![CDATA[
http://tv4-prism.eyevinn-test-adserver.auto.prod.osaas.io/api/v1/sessions/331cea0b-f9a0-4ad3-b07c-e552f003316d/tracking?adId=PLAY_MINITRAILER_BACHELORETTE_5_SEK_annandag_7&progress=75
                      ]]></Tracking>
                      <Tracking event="complete"><![CDATA[
http://tv4-prism.eyevinn-test-adserver.auto.prod.osaas.io/api/v1/sessions/331cea0b-f9a0-4ad3-b07c-e552f003316d/tracking?adId=PLAY_MINITRAILER_BACHELORETTE_5_SEK_annandag_7&progress=100
                      ]]></Tracking>
                    </TrackingEvents>
                    <VideoClicks>
                      <ClickThrough id="Eyevinn Test AdServer"><![CDATA[
https://github.com/Eyevinn/test-adserver
                      ]]></ClickThrough>
                    </VideoClicks>
                    <MediaFiles>
                      <MediaFile bitrate="10041" delivery="progressive" height="1080"
                        type="video/mp4" width="1920"><![CDATA[
https://vod.streaming.a2d.tv/promotions/trailers/65ddb610cf302b002a96d95c_PLAY_MINITRAILER_BACHELORETTE_5_SEK_annandag.mp4
                      ]]></MediaFile>
                    </MediaFiles>
                  </Linear>
                </Creative>
              </Creatives>
              <Extensions></Extensions>
            </InLine>
          </Ad>
        </VAST>
      </vmap:VASTAdData>
    </vmap:AdSource>
    <vmap:TrackingEvents>
      <vmap:Tracking event="breakStart"><![CDATA[
 http://tv4-prism.eyevinn-test-adserver.auto.prod.osaas.io/api/v1/sessions/331cea0b-f9a0-4ad3-b07c-e552f003316d/tracking?adId=midroll.ad-3&progress=vmap 
      ]]></vmap:Tracking>
    </vmap:TrackingEvents>
  </vmap:AdBreak>
</vmap:VMAP>